LICENSE.txt
MANIFEST.in
README.rst
setup.cfg
setup.py
aiohttp_ac_hipchat_postgre/__init__.py
aiohttp_ac_hipchat_postgre/store.py
aiohttp_ac_hipchat_postgre.egg-info/PKG-INFO
aiohttp_ac_hipchat_postgre.egg-info/SOURCES.txt
aiohttp_ac_hipchat_postgre.egg-info/dependency_links.txt
aiohttp_ac_hipchat_postgre.egg-info/not-zip-safe
aiohttp_ac_hipchat_postgre.egg-info/requires.txt
aiohttp_ac_hipchat_postgre.egg-info/top_level.txt