Metadata-Version: 1.1
Name: aiohttp-ac-hipchat-postgre
Version: 0.1.dev0
Summary: Postgre store for aiohttp_ac_hipchat
Home-page: https://bitbucket.org/ramiroberrelleza/aiohttp-ac-hipchat-postgre
Author: Ramiro Berrelleza
Author-email: rberrelleza@atlassian.com
License: APLv2
Platform: any
Classifier: Environment :: Web Environment
Classifier: Intended Audience :: Developers
Classifier: License :: OSI Approved :: BSD License
Classifier: Operating System :: OS Independent
Classifier: Programming Language :: Python
Classifier: Topic :: Internet :: WWW/HTTP :: Dynamic Content
Classifier: Topic :: Software Development :: Libraries :: Python Modules
